cbot/__init__.py
cbot/__main__.py
cbot/cbot_cli.py
cbot_cli-0.1.6.dist-info/licenses/LICENSE
cbot_cli-0.1.6.dist-info/METADATA
cbot_cli-0.1.6.dist-info/WHEEL
cbot_cli-0.1.6.dist-info/entry_points.txt
cbot_cli-0.1.6.dist-info/top_level.txt
cbot_cli-0.1.6.dist-info/RECORD
