Metadata-Version: 2.4
Name: cbot-cli
Version: 0.1.6
Summary: A local-first CLI helper for productivity and automation.
Author-email: "Roberto L. Delgado" <roberto@delgadodev.xyz>
License: MIT
Project-URL: Homepage, https://github.com/roskideluge/cbot
Project-URL: Repository, https://github.com/roskideluge/cbot
Project-URL: Issues, https://github.com/roskideluge/cbot/issues
Keywords: cli,productivity,automation,local-first
Classifier: Programming Language :: Python :: 3
Classifier: License :: OSI Approved :: MIT License
Classifier: Operating System :: OS Independent
Classifier: Intended Audience :: End Users/Desktop
Classifier: Environment :: Console
Requires-Python: >=3.7
License-File: LICENSE
Requires-Dist: requests
Requires-Dist: pyperclip
Requires-Dist: openai
Requires-Dist: python-dotenv
Dynamic: license-file
